jupyterlab_solarized_light_theme/__init__.py
jupyterlab_solarized_light_theme/_version.py
jupyterlab_solarized_light_theme/labextension/package.json
jupyterlab_solarized_light_theme/labextension/static/509.e5074631bd93b9f1d7f9.js
jupyterlab_solarized_light_theme/labextension/static/remoteEntry.0a7dd7926393c58ff49e.js
jupyterlab_solarized_light_theme/labextension/static/style.js
jupyterlab_solarized_light_theme/labextension/static/third-party-licenses.json
jupyterlab_solarized_light_theme/labextension/themes/jupyterlab-solarized-light-theme/index.css
jupyterlab_solarized_light_theme/labextension/themes/jupyterlab-solarized-light-theme/index.js
jupyterlab_solarized_light_theme-1.1.0.data/data/share/jupyter/labextensions/jupyterlab-solarized-light-theme/package.json
jupyterlab_solarized_light_theme-1.1.0.data/data/share/jupyter/labextensions/jupyterlab-solarized-light-theme/static/509.e5074631bd93b9f1d7f9.js
jupyterlab_solarized_light_theme-1.1.0.data/data/share/jupyter/labextensions/jupyterlab-solarized-light-theme/static/remoteEntry.0a7dd7926393c58ff49e.js
jupyterlab_solarized_light_theme-1.1.0.data/data/share/jupyter/labextensions/jupyterlab-solarized-light-theme/static/style.js
jupyterlab_solarized_light_theme-1.1.0.data/data/share/jupyter/labextensions/jupyterlab-solarized-light-theme/static/third-party-licenses.json
jupyterlab_solarized_light_theme-1.1.0.data/data/share/jupyter/labextensions/jupyterlab-solarized-light-theme/themes/jupyterlab-solarized-light-theme/index.css
jupyterlab_solarized_light_theme-1.1.0.data/data/share/jupyter/labextensions/jupyterlab-solarized-light-theme/themes/jupyterlab-solarized-light-theme/index.js
jupyterlab_solarized_light_theme-1.1.0.data/data/share/jupyter/labextensions/jupyterlab-solarized-light-theme/install.json
jupyterlab_solarized_light_theme-1.1.0.dist-info/METADATA
jupyterlab_solarized_light_theme-1.1.0.dist-info/WHEEL
jupyterlab_solarized_light_theme-1.1.0.dist-info/licenses/LICENSE
jupyterlab_solarized_light_theme-1.1.0.dist-info/RECORD
