Metadata-Version: 2.4
Name: jupyterlab_solarized_light_theme
Version: 1.1.0
Summary: Solarized light theme for Jupyterlab.
Project-URL: Homepage, https://github.com/mswolman/jupyterlab-solarized-light-theme/
Project-URL: Bug Tracker, https://github.com/mswolman/jupyterlab-solarized-light-theme/issues
Project-URL: Repository, https://github.com/mswolman/jupyterlab-solarized-light-theme.git
Author-email: Michael Wolman <michael.s.wolman@gmail.com>
License: BSD 3-Clause License
License-File: LICENSE
Keywords: jupyter,jupyterlab,jupyterlab-extension,jupyterlab-theme
Classifier: Framework :: Jupyter
Classifier: Framework :: Jupyter :: JupyterLab
Classifier: Framework :: Jupyter :: JupyterLab :: 4
Classifier: Framework :: Jupyter :: JupyterLab :: Extensions
Classifier: Framework :: Jupyter :: JupyterLab :: Extensions :: Prebuilt
Classifier: Framework :: Jupyter :: JupyterLab :: Extensions :: Themes
Classifier: License :: OSI Approved :: BSD License
Classifier: Programming Language :: Python
Classifier: Programming Language :: Python :: 3
Classifier: Programming Language :: Python :: 3.10
Classifier: Programming Language :: Python :: 3.11
Classifier: Programming Language :: Python :: 3.12
Classifier: Programming Language :: Python :: 3.13
Classifier: Programming Language :: Python :: 3.14
Requires-Python: >=3.10
